README.rst
setup.py
python_sourcemaps.egg-info/PKG-INFO
python_sourcemaps.egg-info/SOURCES.txt
python_sourcemaps.egg-info/dependency_links.txt
python_sourcemaps.egg-info/top_level.txt
sourcemaps/__init__.py