Metadata-Version: 1.1
Name: python-sourcemaps
Version: 1.0
Summary: Python library for parsing and generating source maps
Home-page: https://bitbucket.org/allbuttonspressed/python-sourcemaps
Author: Waldemar Kornewald
Author-email: wkornewald@gmail.com
License: BSD
Platform: any
Classifier: Development Status :: 5 - Production/Stable
Classifier: Environment :: Web Environment
Classifier: Intended Audience :: Developers
Classifier: Operating System :: OS Independent
Classifier: Programming Language :: Python
Classifier: Programming Language :: Python :: 2.7
Classifier: Programming Language :: Python :: 3.3
Classifier: License :: OSI Approved :: BSD License
